ykps/__init__.py
ykps/actions.py
ykps/cli.py
ykps/info.py
ykps/utils.py
ykps_x-0.1.3.dist-info/LICENSE
ykps_x-0.1.3.dist-info/METADATA
ykps_x-0.1.3.dist-info/WHEEL
ykps_x-0.1.3.dist-info/entry_points.txt
ykps_x-0.1.3.dist-info/top_level.txt
ykps_x-0.1.3.dist-info/RECORD
